heatmiserv3/__init__.py
heatmiserv3/config.yml
heatmiserv3/connection.py
heatmiserv3/constants.py
heatmiserv3/heatmiser.py
heatmiserv3-2.0.3.dist-info/LICENSE.TXT
heatmiserv3-2.0.3.dist-info/METADATA
heatmiserv3-2.0.3.dist-info/WHEEL
heatmiserv3-2.0.3.dist-info/RECORD
