Metadata-Version: 2.1
Name: heatmiserv3
Version: 2.0.3
Summary: A library to interact with Heatmiser Themostats using V3 protocol.
License: MIT
Author: Andy Loughran
Author-email: andy@lockran.com
Requires-Python: >=3.9,<4.0
Classifier: License :: OSI Approved :: MIT License
Classifier: Programming Language :: Python :: 3
Classifier: Programming Language :: Python :: 3.9
Classifier: Programming Language :: Python :: 3.10
Classifier: Programming Language :: Python :: 3.11
Classifier: Programming Language :: Python :: 3.12
Requires-Dist: appdirs (>=1.4.4,<2.0.0)
Requires-Dist: importlib-resources (>=6.1.1,<7.0.0)
Requires-Dist: pyserial (>=3.5,<4.0)
Requires-Dist: pyserial-asyncio (>=0.6,<0.7)
Requires-Dist: pyyaml (>=6.0.1,<7.0.0)
